odoo10_addon_purchase_order_line_invoicing-10.0.1.0.0.99.dev14-py3.8-nspkg.pth
odoo/addons/purchase_order_line_invoicing/README.rst
odoo/addons/purchase_order_line_invoicing/__init__.py
odoo/addons/purchase_order_line_invoicing/__manifest__.py
odoo/addons/purchase_order_line_invoicing/i18n/purchase_order_line_invoicing.pot
odoo/addons/purchase_order_line_invoicing/models/__init__.py
odoo/addons/purchase_order_line_invoicing/models/res_partner.py
odoo/addons/purchase_order_line_invoicing/static/description/icon.png
odoo/addons/purchase_order_line_invoicing/tests/__init__.py
odoo/addons/purchase_order_line_invoicing/tests/test_purchase_order_line_invoicing_wizard.py
odoo/addons/purchase_order_line_invoicing/views/res_partner_views.xml
odoo/addons/purchase_order_line_invoicing/wizards/__init__.py
odoo/addons/purchase_order_line_invoicing/wizards/purchase_order_line_invoicing_wizard.py
odoo/addons/purchase_order_line_invoicing/wizards/purchase_order_line_invoicing_wizard.xml
odoo10_addon_purchase_order_line_invoicing-10.0.1.0.0.99.dev14.dist-info/METADATA
odoo10_addon_purchase_order_line_invoicing-10.0.1.0.0.99.dev14.dist-info/WHEEL
odoo10_addon_purchase_order_line_invoicing-10.0.1.0.0.99.dev14.dist-info/namespace_packages.txt
odoo10_addon_purchase_order_line_invoicing-10.0.1.0.0.99.dev14.dist-info/top_level.txt
odoo10_addon_purchase_order_line_invoicing-10.0.1.0.0.99.dev14.dist-info/RECORD
