Metadata-Version: 2.1
Name: odoo10-addon-purchase-order-line-invoicing
Version: 10.0.1.0.0.99.dev14
Summary: Allows to invoice lines of multiple purchase orders
Home-page: https://github.com/OCA/purchase-workflow
Author: ACSONE SA/NV,Odoo Community Association (OCA)
Author-email: support@odoo-community.org
License: AGPL-3
Platform: UNKNOWN
Classifier: Programming Language :: Python
Classifier: Framework :: Odoo
Classifier: License :: OSI Approved :: GNU Affero General Public License v3
Requires-Python: ~=2.7
Requires-Dist: odoo (<10.1dev,>=10.0)
